LICENSE.txt
MANIFEST.in
README.md
setup.cfg
setup.py
GhuConst/.DS_Store
GhuConst/__init__.py
GhuConst/codata.txt
GhuConst/const.py
GhuConst/data.py
GhuConst.egg-info/PKG-INFO
GhuConst.egg-info/SOURCES.txt
GhuConst.egg-info/dependency_links.txt
GhuConst.egg-info/top_level.txt
GhuConst/.idea/.gitignore
GhuConst/.idea/GhuConst.iml
GhuConst/.idea/misc.xml
GhuConst/.idea/modules.xml
GhuConst/.idea/workspace.xml
GhuConst/.idea/inspectionProfiles/Project_Default.xml
GhuConst/.idea/inspectionProfiles/profiles_settings.xml
GhuConst/__pycache__/__init__.cpython-37.pyc
GhuConst/__pycache__/const.cpython-37.pyc
GhuConst/__pycache__/data.cpython-37.pyc