Metadata-Version: 2.1
Name: GhuConst
Version: 0.1.5
Summary: Fundamental Physical Constants and their units
Home-page: https://github.com/ghurone/GhuConst
Author: Erick Ghuron
Author-email: ghuron@usp.br
License: MIT
Keywords: physics units constants value codata
Platform: UNKNOWN
Classifier: Development Status :: 5 - Production/Stable
Classifier: Intended Audience :: Developers
Classifier: License :: OSI Approved :: MIT License
Classifier: Natural Language :: English
Classifier: Operating System :: OS Independent
Classifier: Topic :: Software Development :: Internationalization
Classifier: Topic :: Scientific/Engineering :: Physics
